coflux/__init__.py
coflux/__main__.py
coflux/blobs.py
coflux/config.py
coflux/context.py
coflux/decorators.py
coflux/execution.py
coflux/loader.py
coflux/models.py
coflux/serialisation.py
coflux/server.py
coflux/types.py
coflux/utils.py
coflux/version.py
coflux/worker.py
coflux-0.8.1.dist-info/METADATA
coflux-0.8.1.dist-info/WHEEL
coflux-0.8.1.dist-info/entry_points.txt
coflux-0.8.1.dist-info/RECORD
